pytariff/__init__.py
pytariff/_internal/applied_interval.py
pytariff/_internal/defined_interval.py
pytariff/_internal/helper.py
pytariff/core/__init__.py
pytariff/core/billing.py
pytariff/core/block.py
pytariff/core/charge.py
pytariff/core/day.py
pytariff/core/interval.py
pytariff/core/rate.py
pytariff/core/reset.py
pytariff/core/typing.py
pytariff/core/unit.py
pytariff/core/dataframe/cost.py
pytariff/core/dataframe/extra.py
pytariff/core/dataframe/profile.py
pytariff/core/dataframe/typing.py
pytariff/core/tariff/__init__.py
pytariff/core/tariff/block_tariff.py
pytariff/core/tariff/consumption_tariff.py
pytariff/core/tariff/demand_tariff.py
pytariff/core/tariff/generic_tariff.py
pytariff/core/tariff/single_rate_tariff.py
pytariff/core/tariff/time_of_use_tariff.py
pytariff-0.0.3.dist-info/LICENSE.txt
pytariff-0.0.3.dist-info/METADATA
pytariff-0.0.3.dist-info/WHEEL
pytariff-0.0.3.dist-info/top_level.txt
pytariff-0.0.3.dist-info/RECORD
