Metadata-Version: 2.1
Name: pytariff
Version: 0.0.3
Summary: For representing generic electrical tariffs
Project-URL: Homepage, https://github.com/Ecaloota/pytariff
Project-URL: Issues, https://github.com/Ecaloota/pytariff/issues
Classifier: Programming Language :: Python :: 3
Classifier: Operating System :: OS Independent
Requires-Python: >=3.12
License-File: LICENSE.txt
Requires-Dist: holidays >=0.41
Requires-Dist: numpy >=1.26.3
Requires-Dist: pandas >=2.2.0
Requires-Dist: pandera >=0.18.0
Requires-Dist: plotly >=5.18.0
Requires-Dist: pyarrow >=15.0.0
Requires-Dist: pydantic >=2.5.3
Requires-Dist: pydantic-core >=2.14.6
Provides-Extra: dev
Requires-Dist: flake8 ; extra == 'dev'
Requires-Dist: mypy ; extra == 'dev'
Requires-Dist: black ; extra == 'dev'
Provides-Extra: test
Requires-Dist: pytest ; extra == 'test'
